onesignal_flet/__init__.py
onesignal_flet/control.py
onesignal_flet-0.2.0.dist-info/LICENSE
onesignal_flet-0.2.0.dist-info/METADATA
onesignal_flet-0.2.0.dist-info/WHEEL
onesignal_flet-0.2.0.dist-info/RECORD
