Metadata-Version: 2.1
Name: onesignal-flet
Version: 0.2.0
Summary: Flutter OneSignal package integration for Python Flet.
License: MIT
Author: brunobrown
Author-email: brunobrown.86@gmail.com
Requires-Python: >=3.12,<4.0
Classifier: Development Status :: 5 - Production/Stable
Classifier: Intended Audience :: Developers
Classifier: License :: OSI Approved :: MIT License
Classifier: Natural Language :: English
Classifier: Natural Language :: Portuguese (Brazilian)
Classifier: Operating System :: OS Independent
Classifier: Programming Language :: Python :: 3
Classifier: Programming Language :: Python :: 3.12
Classifier: Topic :: Software Development :: Debuggers
Requires-Dist: flet (>=0.26.0,<0.27.0)
Project-URL: Bug Tracker, https://github.com/brunobrown/onesignal-flet/issues
Project-URL: GitHub, https://github.com/brunobrown/onesignal-flet
